goal/__init__.py
goal/py.typed
goal/geometry/__init__.py
goal/geometry/exponential_family/__init__.py
goal/geometry/exponential_family/base.py
goal/geometry/exponential_family/combinators.py
goal/geometry/exponential_family/harmonium.py
goal/geometry/exponential_family/hierarchical.py
goal/geometry/manifold/__init__.py
goal/geometry/manifold/base.py
goal/geometry/manifold/combinators.py
goal/geometry/manifold/linear.py
goal/geometry/manifold/matrix.py
goal/geometry/manifold/optimizer.py
goal/geometry/manifold/subspace.py
goal/geometry/manifold/util.py
goal/models/__init__.py
goal/models/base/__init__.py
goal/models/base/categorical.py
goal/models/base/poisson.py
goal/models/base/von_mises.py
goal/models/base/gaussian/__init__.py
goal/models/base/gaussian/boltzmann.py
goal/models/base/gaussian/generalized.py
goal/models/base/gaussian/normal.py
goal/models/graphical/__init__.py
goal/models/graphical/instances.py
goal/models/graphical/lgm.py
goal/models/graphical/mixture.py
goal_jax-0.0.1.dist-info/LICENSE
goal_jax-0.0.1.dist-info/METADATA
goal_jax-0.0.1.dist-info/WHEEL
goal_jax-0.0.1.dist-info/top_level.txt
goal_jax-0.0.1.dist-info/RECORD
