Metadata-Version: 2.2
Name: goal-jax
Version: 0.0.1
Summary: (G)eometric (O)ptimiz(A)tion (L)ibraries
License: MIT
License-File: LICENSE
Requires-Dist: jax
Requires-Dist: optax
Provides-Extra: test
Requires-Dist: pytest>=7.0; extra == "test"
Requires-Dist: pytest-cov>=4.0; extra == "test"
Provides-Extra: examples
Requires-Dist: matplotlib; extra == "examples"
Requires-Dist: scipy; extra == "examples"
Requires-Dist: scikit-learn; extra == "examples"
Requires-Dist: scipy-stubs; extra == "examples"
Requires-Dist: seaborn; extra == "examples"
Provides-Extra: gpu
Requires-Dist: jax[cuda12]; extra == "gpu"
